arb_shared_dependencies/__init__.py
arb_shared_dependencies/config.py
arb_shared_dependencies-0.3.0.dist-info/LICENSE
arb_shared_dependencies-0.3.0.dist-info/METADATA
arb_shared_dependencies-0.3.0.dist-info/WHEEL
arb_shared_dependencies-0.3.0.dist-info/top_level.txt
arb_shared_dependencies-0.3.0.dist-info/RECORD
