Metadata-Version: 2.1
Name: arb-shared-dependencies
Version: 0.3.0
Summary: Shared utilities for Arbitrum development
Home-page: https://github.com/justmert/arb-shared-dependencies
Author: justmert
Author-email: 
License: Apache-2.0
Classifier: Programming Language :: Python :: 3
Classifier: License :: OSI Approved :: MIT License
Classifier: Operating System :: OS Independent
Requires-Python: >=3.8
License-File: LICENSE
Requires-Dist: web3>=6.3.0
Requires-Dist: python-dotenv>=1.0.0
